owa/ocap/__init__.py
owa/ocap/recorder.py
owa/ocap/utils.py
ocap-0.6.1.post1.dist-info/METADATA
ocap-0.6.1.post1.dist-info/WHEEL
ocap-0.6.1.post1.dist-info/entry_points.txt
ocap-0.6.1.post1.dist-info/licenses/LICENSE
ocap-0.6.1.post1.dist-info/RECORD
