Metadata-Version: 2.4
Name: ocap
Version: 0.6.1.post1
Summary: High-performance, omnimodal desktop recorder for Windows
License: MIT
License-File: LICENSE
Requires-Python: >=3.11
Requires-Dist: loguru>=0.7.3
Requires-Dist: mcap-owa-support==0.6.1
Requires-Dist: owa-core==0.6.1
Requires-Dist: owa-env-desktop==0.6.1
Requires-Dist: owa-env-gst==0.6.1
Requires-Dist: owa-msgs==0.6.1
Requires-Dist: tqdm>=4.67.1
Requires-Dist: typer>=0.19.2
